rhythmic/__init__.py
rhythmic/db.py
rhythmic/general.py
rhythmic/logger.py
rhythmic-0.0.11.dist-info/METADATA
rhythmic-0.0.11.dist-info/WHEEL
rhythmic-0.0.11.dist-info/top_level.txt
rhythmic-0.0.11.dist-info/RECORD
