Metadata-Version: 2.1
Name: rhythmic
Version: 0.0.11
Summary: Python Bicycle Patterns
Home-page: https://github.com/PycT/Rhythmic
Author: Rustem Zakiev
Author-email: rustem.zakiev@gmail.com
License: UNKNOWN
Platform: UNKNOWN
Classifier: Development Status :: 3 - Alpha
Classifier: Intended Audience :: Developers
Classifier: Topic :: Software Development
Classifier: License :: OSI Approved :: Apache Software License
Classifier: Programming Language :: Python :: 3.6
Requires-Python: >=3.0
